setup.py
lintpy/__init__.py
lintpy.egg-info/PKG-INFO
lintpy.egg-info/SOURCES.txt
lintpy.egg-info/dependency_links.txt
lintpy.egg-info/not-zip-safe
lintpy.egg-info/top_level.txt