Metadata-Version: 1.0
Name: lintpy
Version: 0.1
Summary: The funniest joke in the world
Home-page: http://github.com/abhinavralhan/lintpy
Author: abhinavralhan
Author-email: abhinav.ralhan1@gmail.com
License: MIT
Platform: UNKNOWN
